LICENSE.txt
MANIFEST.in
README.rst
setup.cfg
setup.py
sphinxcontrib/__init__.py
sphinxcontrib/findanything/__init__.py
sphinxcontrib/findanything/css/findanything.css
sphinxcontrib/findanything/javascript/fuzzyfinder.js
sphinxcontrib/findanything/javascript/jquery-1.8.0.min.js
sphinxcontrib/findanything/javascript/jquery.cookie.js
sphinxcontrib/findanything/javascript/jquery.cursor.min.js
sphinxcontrib/findanything/javascript/jquery.fuzzyfind.js
sphinxcontrib/findanything/javascript/jquery.keymap.min.js
sphinxcontrib/findanything/javascript/jquery.simplemodal.1.4.3.min.js
sphinxcontrib_findanything.egg-info/PKG-INFO
sphinxcontrib_findanything.egg-info/SOURCES.txt
sphinxcontrib_findanything.egg-info/dependency_links.txt
sphinxcontrib_findanything.egg-info/namespace_packages.txt
sphinxcontrib_findanything.egg-info/not-zip-safe
sphinxcontrib_findanything.egg-info/requires.txt
sphinxcontrib_findanything.egg-info/top_level.txt