Metadata-Version: 1.1
Name: sphinxcontrib-findanything
Version: 0.2
Summary: Sphinx "FindAnything" extension
Home-page: http://bitbucket.org/birkenfeld/sphinx-contrib
Author: Kay-Uwe (Kiwi) Lorenz
Author-email: kiwi@franka.dyndns.org
License: BSD
Download-URL: http://pypi.python.org/pypi/sphinxcontrib-findanything
Platform: any
Classifier: Development Status :: 4 - Beta
Classifier: Environment :: Console
Classifier: Environment :: Web Environment
Classifier: Intended Audience :: Developers
Classifier: License :: OSI Approved :: BSD License
Classifier: Operating System :: OS Independent
Classifier: Programming Language :: Python
Classifier: Topic :: Documentation
Classifier: Topic :: Utilities
